topsis/topsis.py
Topsis_IshitBajaj_101903692-1.0.0.dist-info/METADATA
Topsis_IshitBajaj_101903692-1.0.0.dist-info/WHEEL
Topsis_IshitBajaj_101903692-1.0.0.dist-info/entry_points.txt
Topsis_IshitBajaj_101903692-1.0.0.dist-info/top_level.txt
Topsis_IshitBajaj_101903692-1.0.0.dist-info/RECORD
